downink/__init__.py
downink/downink.py
downink/termcolor.py
downink-0.0.1.data/scripts/downink
downink-0.0.1.dist-info/LICENSE
downink-0.0.1.dist-info/METADATA
downink-0.0.1.dist-info/WHEEL
downink-0.0.1.dist-info/top_level.txt
downink-0.0.1.dist-info/RECORD
