Metadata-Version: 2.1
Name: downink
Version: 0.0.1
Summary: Download resources from the internet with a single command.
Home-page: http://github.com/mentix02/downink
Author: mentix02
Author-email: manan.yadav02@gmail.com
License: MIT
Platform: UNKNOWN
Requires-Python: >=3.2
Requires-Dist: bs4 (==0.0.1)
Requires-Dist: clint (==0.5.1)
